QNodeEditor/__init__.py
QNodeEditor/dialog.py
QNodeEditor/edge.py
QNodeEditor/editor.py
QNodeEditor/entry.py
QNodeEditor/node.py
QNodeEditor/scene.py
QNodeEditor/socket.py
QNodeEditor/util.py
QNodeEditor/clipboard/__init__.py
QNodeEditor/clipboard/clipboard.py
QNodeEditor/entries/__init__.py
QNodeEditor/entries/combo_box.py
QNodeEditor/entries/labeled.py
QNodeEditor/entries/text_box.py
QNodeEditor/entries/value_box.py
QNodeEditor/graphics/__init__.py
QNodeEditor/graphics/cutter.py
QNodeEditor/graphics/edge.py
QNodeEditor/graphics/entry.py
QNodeEditor/graphics/node.py
QNodeEditor/graphics/scene.py
QNodeEditor/graphics/socket.py
QNodeEditor/graphics/view.py
QNodeEditor/history/__init__.py
QNodeEditor/history/history.py
QNodeEditor/metas/__init__.py
QNodeEditor/metas/graphics_path_item.py
QNodeEditor/metas/object.py
QNodeEditor/serialise/__init__.py
QNodeEditor/serialise/serialise.py
QNodeEditor/themes/__init__.py
QNodeEditor/themes/dark.py
QNodeEditor/themes/light.py
QNodeEditor/themes/theme.py
QNodeEditor/themes/fonts/DejaVuSans/DejaVuSans-Bold.ttf
QNodeEditor/themes/fonts/DejaVuSans/DejaVuSans-BoldOblique.ttf
QNodeEditor/themes/fonts/DejaVuSans/DejaVuSans-ExtraLight.ttf
QNodeEditor/themes/fonts/DejaVuSans/DejaVuSans-Oblique.ttf
QNodeEditor/themes/fonts/DejaVuSans/DejaVuSans.ttf
QNodeEditor/themes/fonts/DejaVuSans/DejaVuSansCondensed-Bold.ttf
QNodeEditor/themes/fonts/DejaVuSans/DejaVuSansCondensed-BoldOblique.ttf
QNodeEditor/themes/fonts/DejaVuSans/DejaVuSansCondensed-Oblique.ttf
QNodeEditor/themes/fonts/DejaVuSans/DejaVuSansCondensed.ttf
QNodeEditor/themes/img/arrow_dark.svg
QNodeEditor/themes/img/arrow_light.svg
QNodeEditor/widgets/__init__.py
QNodeEditor/widgets/combo_box.py
QNodeEditor/widgets/empty.py
QNodeEditor/widgets/label.py
QNodeEditor/widgets/text_box.py
QNodeEditor/widgets/value_box.py
QNodeEditor-1.0.6.dist-info/LICENSE
QNodeEditor-1.0.6.dist-info/METADATA
QNodeEditor-1.0.6.dist-info/WHEEL
QNodeEditor-1.0.6.dist-info/top_level.txt
QNodeEditor-1.0.6.dist-info/RECORD
