Metadata-Version: 2.1
Name: QNodeEditor
Version: 1.0.6
Summary: Node editor for PyQt5
Author: Jasper Jeuken
License: Copyright (c) 2023, Jasper Jeuken
Project-URL: Homepage, https://github.com/JasperJeuken/QNodeEditor
Project-URL: Github, https://github.com/JasperJeuken/QNodeEditor
Project-URL: Documentation, https://qnodeeditor.readthedocs.io/en/latest/
Keywords: node,editor,pyqt5,pyqt,pyside2,pyside,socket,edge,graph,connection,nodes,qnode,qnodeeditor
Classifier: Development Status :: 4 - Beta
Classifier: Intended Audience :: Developers
Classifier: License :: OSI Approved :: MIT License
Classifier: Natural Language :: English
Classifier: Programming Language :: Python :: 3
Requires-Python: >=3.9
License-File: LICENSE
Requires-Dist: PyQt5 ~=5.15.10
Requires-Dist: networkx ~=3.2.1
Provides-Extra: docs
Requires-Dist: sphinx-toolbox ; extra == 'docs'
Requires-Dist: pydata-sphinx-theme ; extra == 'docs'
Requires-Dist: sphinx-design ; extra == 'docs'
Requires-Dist: sphinx-qt-documentation ; extra == 'docs'
